openvds/__init__.py
openvds/api.py
openvds/asyncmethods.py
openvds/concrt140.dll
openvds/core.cp311-win_amd64.pyd
openvds/msvcp140.dll
openvds/msvcp140_1.dll
openvds/msvcp140_2.dll
openvds/openvds.dll
openvds/vcruntime140.dll
openvds/volumedataaccess.py
openvds/volumedataaccessors.py
openvds-3.4.9.data/data/Attributions.md
openvds-3.4.9.data/data/LICENSE
openvds-3.4.9.data/data/README.txt
openvds-3.4.9.data/data/bin/HueBDS.exe
openvds-3.4.9.data/data/bin/SEGYExport.exe
openvds-3.4.9.data/data/bin/SEGYImport.exe
openvds-3.4.9.data/data/bin/VDSCopy.exe
openvds-3.4.9.data/data/bin/VDSInfo.exe
openvds-3.4.9.data/data/bin/concrt140.dll
openvds-3.4.9.data/data/bin/msvcp140.dll
openvds-3.4.9.data/data/bin/msvcp140_1.dll
openvds-3.4.9.data/data/bin/msvcp140_2.dll
openvds-3.4.9.data/data/bin/openvds-javacpp.dll
openvds-3.4.9.data/data/bin/openvds.dll
openvds-3.4.9.data/data/bin/segyutils.dll
openvds-3.4.9.data/data/bin/vcruntime140.dll
openvds-3.4.9.data/data/include/OpenVDS/CoordinateTransformer.h
openvds-3.4.9.data/data/include/OpenVDS/Error.h
openvds-3.4.9.data/data/include/OpenVDS/Exceptions.h
openvds-3.4.9.data/data/include/OpenVDS/GlobalMetadataCommon.h
openvds-3.4.9.data/data/include/OpenVDS/GlobalState.h
openvds-3.4.9.data/data/include/OpenVDS/IJKCoordinateTransformer.h
openvds-3.4.9.data/data/include/OpenVDS/KnownMetadata.h
openvds-3.4.9.data/data/include/OpenVDS/Log.h
openvds-3.4.9.data/data/include/OpenVDS/Matrix.h
openvds-3.4.9.data/data/include/OpenVDS/MetadataAccess.h
openvds-3.4.9.data/data/include/OpenVDS/MetadataContainer.h
openvds-3.4.9.data/data/include/OpenVDS/MetadataKey.h
openvds-3.4.9.data/data/include/OpenVDS/OpenVDS.h
openvds-3.4.9.data/data/include/OpenVDS/OpenVDSInterface.h
openvds-3.4.9.data/data/include/OpenVDS/OpenVDSVersion.h
openvds-3.4.9.data/data/include/OpenVDS/Optional.h
openvds-3.4.9.data/data/include/OpenVDS/Range.h
openvds-3.4.9.data/data/include/OpenVDS/ValueConversion.h
openvds-3.4.9.data/data/include/OpenVDS/ValueRangeEstimator.h
openvds-3.4.9.dist-info/LICENSE
openvds-3.4.9.dist-info/METADATA
openvds-3.4.9.dist-info/WHEEL
openvds-3.4.9.dist-info/top_level.txt
openvds-3.4.9.dist-info/RECORD
