Metadata-Version: 2.1
Name: openvds
Version: 3.4.9
Summary: Open-source implementation of the Volume Data Store (VDS) standard for fast random access to multi-dimensional volumetric data.
Home-page: https://bluware.com/data-solutions/vds
Author: The Open Group / Bluware, Inc.
Maintainer: OpenVDS Developers
Maintainer-email: openvds@bluware.com
License: Attribution-NoDerivatives 4.0 International
Download-URL: https://downloads.bluware.com/ui/native/Releases-OpenVDSPlus/2.1
Project-URL: Bug Tracker, https://community.opengroup.org/osdu/platform/domain-data-mgmt-services/seismic/open-vds/-/issues
Project-URL: Documentation, https://osdu.pages.opengroup.org/platform/domain-data-mgmt-services/seismic/open-vds/
Project-URL: Source Code, https://community.opengroup.org/osdu/platform/domain-data-mgmt-services/seismic/open-vds
Platform: Windows
Platform: Linux
Requires-Dist: numpy
